fm_tools/__init__.py
fm_tools/benchexec_helper.py
fm_tools/download.py
fm_tools/exceptions.py
fm_tools/files.py
fm_tools/fmdata.py
fm_tools/run.py
fm_tools/types.py
fm_tools/zenodo.py
fm_data-0.2.1.dist-info/METADATA
fm_data-0.2.1.dist-info/WHEEL
fm_data-0.2.1.dist-info/RECORD
